<Properties StartupConfiguration="{70C7B7A1-068A-61C8-4D07-9F1D01F7A0BC}|">
  <MonoDevelop.Ide.Workbench ActiveDocument="Assets/Scripts/uiManger.cs">
    <Files>
      <File FileName="Assets/Scripts/uiManger.cs" Line="27" Column="41" />
      <File FileName="Assets/Scripts/player.cs" Line="126" Column="17" />
      <File FileName="Assets/Scripts/MapManger.cs" Line="1" Column="1" />
    </Files>
    <Pads>
      <Pad Id="ProjectPad">
        <State name="__root__">
          <Node name="CubeRun" expanded="True">
            <Node name="Assets" expanded="True">
              <Node name="Scripts" expanded="True">
                <Node name="uiManger.cs" selected="True" />
              </Node>
            </Node>
          </Node>
        </State>
      </Pad>
    </Pads>
  </MonoDevelop.Ide.Workbench>
  <MonoDevelop.Ide.DebuggingService.PinnedWatches />
  <MonoDevelop.Ide.Workspace ActiveConfiguration="Debug" />
  <MonoDevelop.Ide.ItemProperties.Assembly-CSharp PreferredExecutionTarget="04753933-f8af-4f1e-99bb-580860496da8" />
  <MonoDevelop.Ide.DebuggingService.Breakpoints>
    <BreakpointStore />
  </MonoDevelop.Ide.DebuggingService.Breakpoints>
  <MultiItemStartupConfigurations />
</Properties>